fps_retrolab/__init__.py
fps_retrolab/main.py
fps_retrolab/routes.py
fps_retrolab-0.4.2.dist-info/METADATA
fps_retrolab-0.4.2.dist-info/WHEEL
fps_retrolab-0.4.2.dist-info/entry_points.txt
fps_retrolab-0.4.2.dist-info/licenses/COPYING.md
fps_retrolab-0.4.2.dist-info/RECORD
