Metadata-Version: 2.1
Name: fps_retrolab
Version: 0.4.2
Summary: An FPS plugin for the RetroLab API
Project-URL: Homepage, https://jupyter.org
Author-email: Jupyter Development Team <jupyter@googlegroups.com>
License: BSD 3-Clause License
License-File: COPYING.md
Keywords: fastapi,jupyter,plugins,server
Requires-Python: >=3.8
Requires-Dist: jupyverse-api<1,>=0.1.2
Requires-Dist: retrolab
